odoo10_addon_product_attribute_set-10.0.1.1.0.99.dev5-py3.8-nspkg.pth
odoo/addons/product_attribute_set/README.rst
odoo/addons/product_attribute_set/__init__.py
odoo/addons/product_attribute_set/__manifest__.py
odoo/addons/product_attribute_set/demo/product_attribute.xml
odoo/addons/product_attribute_set/models/__init__.py
odoo/addons/product_attribute_set/models/product.py
odoo/addons/product_attribute_set/models/product_category.py
odoo/addons/product_attribute_set/models/res_company.py
odoo/addons/product_attribute_set/readme/CONTRIBUTORS.rst
odoo/addons/product_attribute_set/readme/DESCRIPTION.rst
odoo/addons/product_attribute_set/readme/ROADMAP.rst
odoo/addons/product_attribute_set/readme/USAGE.rst
odoo/addons/product_attribute_set/static/description/icon.png
odoo/addons/product_attribute_set/static/description/index.html
odoo/addons/product_attribute_set/views/product.xml
odoo/addons/product_attribute_set/views/product_category.xml
odoo10_addon_product_attribute_set-10.0.1.1.0.99.dev5.dist-info/METADATA
odoo10_addon_product_attribute_set-10.0.1.1.0.99.dev5.dist-info/WHEEL
odoo10_addon_product_attribute_set-10.0.1.1.0.99.dev5.dist-info/namespace_packages.txt
odoo10_addon_product_attribute_set-10.0.1.1.0.99.dev5.dist-info/top_level.txt
odoo10_addon_product_attribute_set-10.0.1.1.0.99.dev5.dist-info/RECORD
